nobspy/__init__.py
nobspy/alembic.py
nobspy/cli.py
nobspy/docker.py
nobspy/models.py
nobspy/queue.py
nobspy/resources.py
nobspy/runners.py
nobspy/secrets.py
nobspy/worker.py
nobspy-0.1.16.dist-info/WHEEL
nobspy-0.1.16.dist-info/entry_points.txt
nobspy-0.1.16.dist-info/METADATA
nobspy-0.1.16.dist-info/RECORD
