Metadata-Version: 2.3
Name: nobspy
Version: 0.1.16
Summary: A project that makes it easier to develope and deploy Python projects
Requires-Dist: click>=8.3.0
Requires-Dist: pydantic-settings>=2.11.0
Requires-Dist: pydantic>=2.12.0
Requires-Dist: fastapi[standard]>=0.119.0
Requires-Dist: pytest>=9.0.1
Requires-Dist: pytest-asyncio>=1.3.0
Requires-Dist: debugpy>=1.8.17
Requires-Dist: pytest-mock>=3.15.1
Requires-Dist: nats-py[nkeys]>=2.12.0
Requires-Dist: docker>=7.1.0
Requires-Dist: tomli>=2.3.0
Requires-Dist: rich>=13.0.0
Requires-Dist: python-logging-loki ; extra == 'logging'
Requires-Dist: prometheus-client ; extra == 'metrics'
Requires-Dist: python-logging-loki ; extra == 'observability'
Requires-Dist: prometheus-client ; extra == 'observability'
Requires-Python: >=3.10
Provides-Extra: logging
Provides-Extra: metrics
Provides-Extra: observability
